aiovalorant/__init__.py
aiovalorant/client.py
aiovalorant/exceptions.py
aiovalorant/traits.py
aiovalorant/models/__init__.py
aiovalorant/models/agents.py
aiovalorant/models/buddies.py
aiovalorant/models/bundles.py
aiovalorant/models/ceremonies.py
aiovalorant/models/competitive_tiers.py
aiovalorant/models/content_tiers.py
aiovalorant/models/contracts.py
aiovalorant/models/currencies.py
aiovalorant/models/events.py
aiovalorant/models/gamemodes.py
aiovalorant/models/gear.py
aiovalorant/models/level_borders.py
aiovalorant/models/maps.py
aiovalorant/models/player_cards.py
aiovalorant/models/player_titles.py
aiovalorant/models/seasons.py
aiovalorant/models/sprays.py
aiovalorant/models/themes.py
aiovalorant/models/version.py
aiovalorant/models/weapons.py
aiovalorant-0.1.0.dist-info/WHEEL
aiovalorant-0.1.0.dist-info/METADATA
aiovalorant-0.1.0.dist-info/RECORD
