Metadata-Version: 2.1
Name: aiovalorant
Version: 0.1.0
Summary: An async wrapper for Valorant API.
Author-email: Shinobou <86394469+Shinobou@users.noreply.github.com>
Requires-Dist: pydantic~=1.9.1
Requires-Dist: aiosonic~=0.14.1
Requires-Dist: black ; extra == "dev"
Requires-Dist: mypy ; extra == "dev"
Provides-Extra: dev
